{
  "voc_eval_res": {
    "precision": 56.8,
    "recall": 24.4828,
    "f-score": 34.2169
  },
  "KL_res": {
    "KL divergence": 3.634904013441239,
    "Euclidean Dist.": 0.18553785831813577,
    "WER": 0.7711711711711712,
    "CER": 0.6302250803858521,
    "Cosine Dist.": 0.356806996187208
  },
  "occ_eval_res": {
    "precision": 60.793,
    "recall": 24.8649,
    "f-score": 35.2941
  },
  "clean_eval": {
    "f-score": 26.441631504922647,
    "precision": 19.10569105691057,
    "recall": 42.922374429223744,
    "tp": 94,
    "fp": 398,
    "fn": 125
  },
  "jaccard": [
    0.6119246861924686
  ],
  "braycurtis": [
    0.4519642857142857
  ],
  "dice": [
    0.440844009042954
  ],
  "cosinus": [
    0.22368609017748498
  ]
}